krules_core/__init__.py
krules_core/arg_processors/__init__.py
krules_core/base_functions/__init__.py
krules_core/base_functions/filters.py
krules_core/base_functions/misc.py
krules_core/base_functions/processing.py
krules_core/base_functions/support/__init__.py
krules_core/base_functions/support/scheduler.py
krules_core/core.py
krules_core/event_types.py
krules_core/exceptions_dumpers.py
krules_core/models.py
krules_core/providers.py
krules_core/route/__init__.py
krules_core/route/dispatcher.py
krules_core/route/router.py
krules_core/subject/__init__.py
krules_core/subject/empty_storage.py
krules_core/subject/storaged_subject.py
krules_core/tests/__init__.py
krules_core/tests/base_functions/__init__.py
krules_core/tests/base_functions/test_filters.py
krules_core/tests/base_functions/test_misc.py
krules_core/tests/base_functions/test_processing.py
krules_core/tests/subject/__init__.py
krules_core/tests/subject/sqlite_storage/__init__.py
krules_core/tests/subject/sqlite_storage/test_sqlitestorage_inmemory.py
krules_core/tests/subject/sqlite_storage/test_sqlitestorage_onfile.py
krules_core/tests/subject/test_empty_storage.py
krules_core/tests/subject/test_storage.py
krules_core/tests/subject/test_storaged_subject.py
krules_core/tests/test_argprocessors.py
krules_core/tests/test_core.py
krules_core/tests/test_router.py
krules_core/utils.py
krules_core-0.12.0.dist-info/AUTHORS
krules_core-0.12.0.dist-info/METADATA
krules_core-0.12.0.dist-info/WHEEL
krules_core-0.12.0.dist-info/RECORD
